emputility/__init__.py
emputility/analysis.py
emputility/emputility.py
emputility/visualiztion.py
Emputility-1.0.0.dist-info/LICENSE
Emputility-1.0.0.dist-info/METADATA
Emputility-1.0.0.dist-info/WHEEL
Emputility-1.0.0.dist-info/top_level.txt
Emputility-1.0.0.dist-info/RECORD
