Metadata-Version: 2.1
Name: Emputility
Version: 1.0.0
Summary: It has many useful tools!
Home-page: https://github.com/lubudack/emputility
Author: EmPoKa
Author-email: blach205@gmail.com
License: UNKNOWN
Platform: UNKNOWN
Classifier: License :: OSI Approved :: MIT License
